{"24":[{"a":"Pseudo-Basil","sc":24,"sv":19,"ec":24,"ev":19,"p":"Pseudo-Basil/Deuteronomy 24_19.toml"},{"a":"Paterius","sc":24,"sv":13,"ec":24,"ev":13,"p":"Paterius/Deuteronomy 24_13.toml"},{"a":"Paterius","sc":24,"sv":6,"ec":24,"ev":6,"p":"Paterius/Deuteronomy 24_6.toml"},{"a":"Augustine of Hippo","sc":24,"sv":1,"ec":24,"ev":1,"p":"Augustine of Hippo/Deuteronomy 24_1.toml"}],"33":[{"a":"Hippolytus of Rome","sc":33,"sv":2,"ec":33,"ev":2,"p":"Hippolytus of Rome/Deuteronomy 33_2.toml"},{"a":"Paterius","sc":33,"sv":9,"ec":33,"ev":9,"p":"Paterius/Deuteronomy 33_9.toml"},{"a":"Paterius","sc":33,"sv":2,"ec":33,"ev":2,"p":"Paterius/Deuteronomy 33_2.toml"},{"a":"Paterius","sc":33,"sv":25,"ec":33,"ev":25,"p":"Paterius/Deuteronomy 33_25.toml"},{"a":"Bonaventure","sc":33,"sv":12,"ec":33,"ev":12,"p":"Bonaventure/Deuteronomy 33_12.toml"},{"a":"Bonaventure","sc":33,"sv":13,"ec":33,"ev":13,"p":"Bonaventure/Deuteronomy 33_13.toml"},{"a":"Bonaventure","sc":33,"sv":19,"ec":33,"ev":19,"p":"Bonaventure/Deuteronomy 33_19.toml"},{"a":"Gregory the Dialogist","sc":33,"sv":2,"ec":33,"ev":2,"p":"Gregory the Dialogist/Deuteronomy 33_2.toml"},{"a":"Ambrose of Milan","sc":33,"sv":17,"ec":33,"ev":17,"p":"Ambrose of Milan/Deuteronomy 33_17.toml"},{"a":"Ambrose of Milan","sc":33,"sv":24,"ec":33,"ev":24,"p":"Ambrose of Milan/Deuteronomy 33_24.toml"},{"a":"Ambrose of Milan","sc":33,"sv":22,"ec":33,"ev":22,"p":"Ambrose of Milan/Deuteronomy 33_22.toml"},{"a":"CS Lewis","sc":33,"sv":27,"ec":33,"ev":27,"p":"CS Lewis/Deuteronomy 33_27.toml"},{"a":"Aphrahat the Persian Sage","sc":33,"sv":6,"ec":33,"ev":6,"p":"Aphrahat the Persian Sage/Deuteronomy 33_6.toml"}],"4":[{"a":"Pseudo-Clement","sc":4,"sv":39,"ec":4,"ev":39,"p":"Pseudo-Clement/Deuteronomy 4_39.toml"},{"a":"Philo of Alexandria","sc":4,"sv":19,"ec":4,"ev":20,"p":"Philo of Alexandria/Deuteronomy 4_19-20.toml"},{"a":"Hebrews","sc":4,"sv":24,"ec":4,"ev":24,"p":"Hebrews/Deuteronomy 4_24.toml"},{"a":"John Chrysostom","sc":4,"sv":33,"ec":4,"ev":33,"p":"John Chrysostom/Deuteronomy 4_33.toml"},{"a":"John Damascene","sc":4,"sv":24,"ec":4,"ev":24,"p":"John Damascene/Deuteronomy 4_24.toml"},{"a":"Ambrose of Milan","sc":4,"sv":24,"ec":4,"ev":24,"p":"Ambrose of Milan/Deuteronomy 4_24.toml"},{"a":"Origen of Alexandria","sc":4,"sv":24,"ec":4,"ev":24,"p":"Origen of Alexandria/Deuteronomy 4_24.toml"},{"a":"Origen of Alexandria","sc":4,"sv":19,"ec":4,"ev":19,"p":"Origen of Alexandria/Deuteronomy 4_19.toml"},{"a":"Origen of Alexandria","sc":4,"sv":38,"ec":4,"ev":38,"p":"Origen of Alexandria/Deuteronomy 4_38.toml"},{"a":"Origen of Alexandria","sc":4,"sv":16,"ec":4,"ev":16,"p":"Origen of Alexandria/Deuteronomy 4_16.toml"},{"a":"Basil of Caesarea","sc":4,"sv":26,"ec":4,"ev":26,"p":"Basil of Caesarea/Deuteronomy 4_26.toml"},{"a":"Jerome","sc":4,"sv":24,"ec":4,"ev":24,"p":"Jerome/Deuteronomy 4_24.toml"}],"32":[{"a":"Novatian","sc":32,"sv":8,"ec":32,"ev":8,"p":"Novatian/Deuteronomy 32_8.toml"},{"a":"Desert Fathers","sc":32,"sv":35,"ec":32,"ev":35,"p":"Desert Fathers/Deuteronomy 32_35.toml"},{"a":"Hilary of Poitiers","sc":32,"sv":39,"ec":32,"ev":39,"p":"Hilary of Poitiers/Deuteronomy 32_39.toml"},{"a":"Paterius","sc":32,"sv":1,"ec":32,"ev":1,"p":"Paterius/Deuteronomy 32_1.toml"},{"a":"Paterius","sc":32,"sv":11,"ec":32,"ev":11,"p":"Paterius/Deuteronomy 32_11.toml"},{"a":"Paterius","sc":32,"sv":13,"ec":32,"ev":13,"p":"Paterius/Deuteronomy 32_13.toml"},{"a":"Paterius","sc":32,"sv":42,"ec":32,"ev":42,"p":"Paterius/Deuteronomy 32_42.toml"},{"a":"Bonaventure","sc":32,"sv":16,"ec":32,"ev":16,"p":"Bonaventure/Deuteronomy 32_16.toml"},{"a":"Bonaventure","sc":32,"sv":27,"ec":32,"ev":27,"p":"Bonaventure/Deuteronomy 32_27.toml"},{"a":"Bonaventure","sc":32,"sv":29,"ec":32,"ev":29,"p":"Bonaventure/Deuteronomy 32_29.toml"},{"a":"Bonaventure","sc":32,"sv":28,"ec":32,"ev":28,"p":"Bonaventure/Deuteronomy 32_28.toml"},{"a":"Bonaventure","sc":32,"sv":2,"ec":32,"ev":2,"p":"Bonaventure/Deuteronomy 32_2.toml"},{"a":"Bonaventure","sc":32,"sv":39,"ec":32,"ev":39,"p":"Bonaventure/Deuteronomy 32_39.toml"},{"a":"Clement of Rome","sc":32,"sv":15,"ec":32,"ev":15,"p":"Clement of Rome/Deuteronomy 32_15.toml"},{"a":"Hebrews","sc":32,"sv":36,"ec":32,"ev":36,"p":"Hebrews/Deuteronomy 32_36.toml"},{"a":"Hebrews","sc":32,"sv":35,"ec":32,"ev":35,"p":"Hebrews/Deuteronomy 32_35.toml"},{"a":"Hebrews","sc":32,"sv":43,"ec":32,"ev":43,"p":"Hebrews/Deuteronomy 32_43.toml"},{"a":"Philoxenus of Mabbug","sc":32,"sv":13,"ec":32,"ev":13,"p":"Philoxenus of Mabbug/Deuteronomy 32_13.toml"},{"a":"Philoxenus of Mabbug","sc":32,"sv":15,"ec":32,"ev":15,"p":"Philoxenus of Mabbug/Deuteronomy 32_15.toml"},{"a":"Philoxenus of Mabbug","sc":32,"sv":14,"ec":32,"ev":14,"p":"Philoxenus of Mabbug/Deuteronomy 32_14.toml"},{"a":"John Chrysostom","sc":32,"sv":15,"ec":32,"ev":15,"p":"John Chrysostom/Deuteronomy 32_15.toml"},{"a":"Romans","sc":32,"sv":21,"ec":32,"ev":21,"p":"Romans/Deuteronomy 32_21.toml"},{"a":"Romans","sc":32,"sv":35,"ec":32,"ev":35,"p":"Romans/Deuteronomy 32_35.toml"},{"a":"Romans","sc":32,"sv":43,"ec":32,"ev":43,"p":"Romans/Deuteronomy 32_43.toml"},{"a":"Gregory the Dialogist","sc":32,"sv":8,"ec":32,"ev":8,"p":"Gregory the Dialogist/Deuteronomy 32_8.toml"},{"a":"John Cassian","sc":32,"sv":7,"ec":32,"ev":7,"p":"John Cassian/Deuteronomy 32_7.toml"},{"a":"Caesarius of Arles","sc":32,"sv":2,"ec":32,"ev":2,"p":"Caesarius of Arles/Deuteronomy 32_2.toml"},{"a":"Gregory of Nyssa","sc":32,"sv":39,"ec":32,"ev":39,"p":"Gregory of Nyssa/Deuteronomy 32_39.toml"},{"a":"Clement of Alexandria","sc":32,"sv":20,"ec":32,"ev":20,"p":"Clement of Alexandria/Deuteronomy 32_20.toml"},{"a":"Clement of Alexandria","sc":32,"sv":10,"ec":32,"ev":10,"p":"Clement of Alexandria/Deuteronomy 32_10.toml"},{"a":"Clement of Alexandria","sc":32,"sv":8,"ec":32,"ev":8,"p":"Clement of Alexandria/Deuteronomy 32_8.toml"},{"a":"Clement of Alexandria","sc":32,"sv":23,"ec":32,"ev":23,"p":"Clement of Alexandria/Deuteronomy 32_23.toml"},{"a":"Ambrose of Milan","sc":32,"sv":11,"ec":32,"ev":11,"p":"Ambrose of Milan/Deuteronomy 32_11.toml"},{"a":"Ambrose of Milan","sc":32,"sv":35,"ec":32,"ev":35,"p":"Ambrose of Milan/Deuteronomy 32_35.toml"},{"a":"Origen of Alexandria","sc":32,"sv":6,"ec":32,"ev":6,"p":"Origen of Alexandria/Deuteronomy 32_6.toml"},{"a":"Origen of Alexandria","sc":32,"sv":4,"ec":32,"ev":4,"p":"Origen of Alexandria/Deuteronomy 32_4.toml"},{"a":"Origen of Alexandria","sc":32,"sv":32,"ec":32,"ev":32,"p":"Origen of Alexandria/Deuteronomy 32_32.toml"},{"a":"Origen of Alexandria","sc":32,"sv":2,"ec":32,"ev":2,"p":"Origen of Alexandria/Deuteronomy 32_2.toml"},{"a":"Basil of Caesarea","sc":32,"sv":39,"ec":32,"ev":39,"p":"Basil of Caesarea/Deuteronomy 32_39.toml"},{"a":"Athanasius of Alexandria","sc":32,"sv":48,"ec":32,"ev":49,"p":"Athanasius of Alexandria/Deuteronomy 32_48-49.toml"},{"a":"Cosmas Indicopleustes","sc":32,"sv":8,"ec":32,"ev":8,"p":"Cosmas Indicopleustes/Deuteronomy 32_8.toml"},{"a":"Augustine of Hippo","sc":32,"sv":50,"ec":32,"ev":50,"p":"Augustine of Hippo/Deuteronomy 32_50.toml"},{"a":"Augustine of Hippo","sc":32,"sv":51,"ec":32,"ev":51,"p":"Augustine of Hippo/Deuteronomy 32_51.toml"},{"a":"Augustine of Hippo","sc":32,"sv":39,"ec":32,"ev":39,"p":"Augustine of Hippo/Deuteronomy 32_39.toml"},{"a":"Jerome","sc":32,"sv":11,"ec":32,"ev":11,"p":"Jerome/Deuteronomy 32_11.toml"},{"a":"Jerome","sc":32,"sv":8,"ec":32,"ev":8,"p":"Jerome/Deuteronomy 32_8.toml"},{"a":"Aphrahat the Persian Sage","sc":32,"sv":39,"ec":32,"ev":39,"p":"Aphrahat the Persian Sage/Deuteronomy 32_39.toml"}],"31":[{"a":"Nicetas of Remesiana","sc":31,"sv":30,"ec":31,"ev":30,"p":"Nicetas of Remesiana/Deuteronomy 31_30.toml"},{"a":"Hebrews","sc":31,"sv":6,"ec":31,"ev":6,"p":"Hebrews/Deuteronomy 31_6.toml"},{"a":"Augustine of Hippo","sc":31,"sv":6,"ec":31,"ev":6,"p":"Augustine of Hippo/Deuteronomy 31_6.toml"}],"6":[{"a":"Desert Fathers","sc":6,"sv":5,"ec":6,"ev":5,"p":"Desert Fathers/Deuteronomy 6_5.toml"},{"a":"Luke","sc":6,"sv":13,"ec":6,"ev":13,"p":"Luke/Deuteronomy 6_13.toml"},{"a":"Luke","sc":6,"sv":16,"ec":6,"ev":16,"p":"Luke/Deuteronomy 6_16.toml"},{"a":"Luke","sc":6,"sv":5,"ec":6,"ev":5,"p":"Luke/Deuteronomy 6_5.toml"},{"a":"Hilary of Poitiers","sc":6,"sv":4,"ec":6,"ev":4,"p":"Hilary of Poitiers/Deuteronomy 6_4.toml"},{"a":"Cassiodorus","sc":6,"sv":5,"ec":6,"ev":5,"p":"Cassiodorus/Deuteronomy 6_5.toml"},{"a":"Bonaventure","sc":6,"sv":4,"ec":6,"ev":4,"p":"Bonaventure/Deuteronomy 6_4.toml"},{"a":"Philoxenus of Mabbug","sc":6,"sv":12,"ec":6,"ev":12,"p":"Philoxenus of Mabbug/Deuteronomy 6_12.toml"},{"a":"Philoxenus of Mabbug","sc":6,"sv":5,"ec":6,"ev":5,"p":"Philoxenus of Mabbug/Deuteronomy 6_5.toml"},{"a":"Mark","sc":6,"sv":5,"ec":6,"ev":5,"p":"Mark/Deuteronomy 6_5.toml"},{"a":"Mark","sc":6,"sv":4,"ec":6,"ev":4,"p":"Mark/Deuteronomy 6_4.toml"},{"a":"John Chrysostom","sc":6,"sv":4,"ec":6,"ev":4,"p":"John Chrysostom/Deuteronomy 6_4.toml"},{"a":"Fulgentius of Ruspe","sc":6,"sv":4,"ec":6,"ev":4,"p":"Fulgentius of Ruspe/Deuteronomy 6_4.toml"},{"a":"Matthew","sc":6,"sv":13,"ec":6,"ev":13,"p":"Matthew/Deuteronomy 6_13.toml"},{"a":"Matthew","sc":6,"sv":16,"ec":6,"ev":16,"p":"Matthew/Deuteronomy 6_16.toml"},{"a":"Matthew","sc":6,"sv":5,"ec":6,"ev":5,"p":"Matthew/Deuteronomy 6_5.toml"},{"a":"Gregory of Nyssa","sc":6,"sv":5,"ec":6,"ev":5,"p":"Gregory of Nyssa/Deuteronomy 6_5.toml"},{"a":"Gregory of Nyssa","sc":6,"sv":4,"ec":6,"ev":4,"p":"Gregory of Nyssa/Deuteronomy 6_4.toml"},{"a":"Ambrose of Milan","sc":6,"sv":5,"ec":6,"ev":5,"p":"Ambrose of Milan/Deuteronomy 6_5.toml"},{"a":"Ambrose of Milan","sc":6,"sv":4,"ec":6,"ev":4,"p":"Ambrose of Milan/Deuteronomy 6_4.toml"},{"a":"Augustine of Hippo","sc":6,"sv":13,"ec":6,"ev":13,"p":"Augustine of Hippo/Deuteronomy 6_13.toml"},{"a":"Augustine of Hippo","sc":6,"sv":5,"ec":6,"ev":5,"p":"Augustine of Hippo/Deuteronomy 6_5.toml"},{"a":"Augustine of Hippo","sc":6,"sv":4,"ec":6,"ev":4,"p":"Augustine of Hippo/Deuteronomy 6_4.toml"},{"a":"Bernard of Clairvaux","sc":6,"sv":5,"ec":6,"ev":5,"p":"Bernard of Clairvaux/Deuteronomy 6_5.toml"}],"5":[{"a":"Eusebius of Caesarea","sc":5,"sv":3,"ec":5,"ev":3,"p":"Eusebius of Caesarea/Deuteronomy 5_3.toml"},{"a":"Ephesians","sc":5,"sv":16,"ec":5,"ev":16,"p":"Ephesians/Deuteronomy 5_16.toml"},{"a":"Mark","sc":5,"sv":16,"ec":5,"ev":16,"p":"Mark/Deuteronomy 5_16.toml"},{"a":"Matthew","sc":5,"sv":16,"ec":5,"ev":16,"p":"Matthew/Deuteronomy 5_16.toml"},{"a":"Cyril of Jerusalem","sc":5,"sv":26,"ec":5,"ev":26,"p":"Cyril of Jerusalem/Deuteronomy 5_26.toml"},{"a":"Ambrose of Milan","sc":5,"sv":31,"ec":5,"ev":31,"p":"Ambrose of Milan/Deuteronomy 5_31.toml"},{"a":"Origen of Alexandria","sc":5,"sv":31,"ec":5,"ev":31,"p":"Origen of Alexandria/Deuteronomy 5_31.toml"},{"a":"Augustine of Hippo","sc":5,"sv":22,"ec":5,"ev":22,"p":"Augustine of Hippo/Deuteronomy 5_22.toml"}],"10":[{"a":"Luke","sc":10,"sv":12,"ec":10,"ev":12,"p":"Luke/Deuteronomy 10_12.toml"},{"a":"Luke","sc":10,"sv":20,"ec":10,"ev":20,"p":"Luke/Deuteronomy 10_20.toml"},{"a":"Justin Martyr","sc":10,"sv":17,"ec":10,"ev":17,"p":"Justin Martyr/Deuteronomy 10_17.toml"},{"a":"Bonaventure","sc":10,"sv":12,"ec":10,"ev":12,"p":"Bonaventure/Deuteronomy 10_12.toml"},{"a":"Mark","sc":10,"sv":12,"ec":10,"ev":12,"p":"Mark/Deuteronomy 10_12.toml"},{"a":"Matthew","sc":10,"sv":12,"ec":10,"ev":12,"p":"Matthew/Deuteronomy 10_12.toml"},{"a":"Matthew","sc":10,"sv":20,"ec":10,"ev":20,"p":"Matthew/Deuteronomy 10_20.toml"},{"a":"Gregory of Nyssa","sc":10,"sv":22,"ec":10,"ev":22,"p":"Gregory of Nyssa/Deuteronomy 10_22.toml"},{"a":"Origen of Alexandria","sc":10,"sv":12,"ec":10,"ev":12,"p":"Origen of Alexandria/Deuteronomy 10_12.toml"},{"a":"1 Corinthians","sc":10,"sv":14,"ec":10,"ev":14,"p":"1 Corinthians/Deuteronomy 10_14.toml"}],"30":[{"a":"Luke","sc":30,"sv":6,"ec":30,"ev":6,"p":"Luke/Deuteronomy 30_6.toml"},{"a":"Bonaventure","sc":30,"sv":11,"ec":30,"ev":11,"p":"Bonaventure/Deuteronomy 30_11.toml"},{"a":"Bonaventure","sc":30,"sv":15,"ec":30,"ev":15,"p":"Bonaventure/Deuteronomy 30_15.toml"},{"a":"Salvian the Presbyter","sc":30,"sv":19,"ec":30,"ev":19,"p":"Salvian the Presbyter/Deuteronomy 30_19.toml"},{"a":"Mark","sc":30,"sv":6,"ec":30,"ev":6,"p":"Mark/Deuteronomy 30_6.toml"},{"a":"Romans","sc":30,"sv":12,"ec":30,"ev":14,"p":"Romans/Deuteronomy 30_12-14.toml"},{"a":"Matthew","sc":30,"sv":6,"ec":30,"ev":6,"p":"Matthew/Deuteronomy 30_6.toml"},{"a":"Caesarius of Arles","sc":30,"sv":19,"ec":30,"ev":19,"p":"Caesarius of Arles/Deuteronomy 30_19.toml"},{"a":"Clement of Alexandria","sc":30,"sv":14,"ec":30,"ev":14,"p":"Clement of Alexandria/Deuteronomy 30_14.toml"},{"a":"Ambrose of Milan","sc":30,"sv":15,"ec":30,"ev":15,"p":"Ambrose of Milan/Deuteronomy 30_15.toml"},{"a":"Origen of Alexandria","sc":30,"sv":14,"ec":30,"ev":14,"p":"Origen of Alexandria/Deuteronomy 30_14.toml"},{"a":"Basil of Caesarea","sc":30,"sv":15,"ec":30,"ev":15,"p":"Basil of Caesarea/Deuteronomy 30_15.toml"},{"a":"CS Lewis","sc":30,"sv":19,"ec":30,"ev":19,"p":"CS Lewis/Deuteronomy 30_19.toml"}],"8":[{"a":"Luke","sc":8,"sv":3,"ec":8,"ev":3,"p":"Luke/Deuteronomy 8_3.toml"},{"a":"Philoxenus of Mabbug","sc":8,"sv":3,"ec":8,"ev":3,"p":"Philoxenus of Mabbug/Deuteronomy 8_3.toml"},{"a":"John Chrysostom","sc":8,"sv":10,"ec":8,"ev":10,"p":"John Chrysostom/Deuteronomy 8_10.toml"},{"a":"Ephrem the Syrian","sc":8,"sv":4,"ec":8,"ev":4,"p":"Ephrem the Syrian/Deuteronomy 8_4.toml"},{"a":"Matthew","sc":8,"sv":3,"ec":8,"ev":3,"p":"Matthew/Deuteronomy 8_3.toml"},{"a":"Clement of Alexandria","sc":8,"sv":18,"ec":8,"ev":18,"p":"Clement of Alexandria/Deuteronomy 8_18.toml"},{"a":"Clement of Alexandria","sc":8,"sv":3,"ec":8,"ev":3,"p":"Clement of Alexandria/Deuteronomy 8_3.toml"},{"a":"Ambrose of Milan","sc":8,"sv":17,"ec":8,"ev":17,"p":"Ambrose of Milan/Deuteronomy 8_17.toml"},{"a":"Ambrose of Milan","sc":8,"sv":4,"ec":8,"ev":4,"p":"Ambrose of Milan/Deuteronomy 8_4.toml"},{"a":"Augustine of Hippo","sc":8,"sv":4,"ec":8,"ev":4,"p":"Augustine of Hippo/Deuteronomy 8_4.toml"}],"22":[{"a":"Gregory of Neocaesarea","sc":22,"sv":1,"ec":22,"ev":4,"p":"Gregory of Neocaesarea/Deuteronomy 22_1-4.toml"},{"a":"Paterius","sc":22,"sv":10,"ec":22,"ev":10,"p":"Paterius/Deuteronomy 22_10.toml"},{"a":"Caesarius of Arles","sc":22,"sv":4,"ec":22,"ev":4,"p":"Caesarius of Arles/Deuteronomy 22_4.toml"},{"a":"Gregory of Nyssa","sc":22,"sv":10,"ec":22,"ev":10,"p":"Gregory of Nyssa/Deuteronomy 22_10.toml"},{"a":"Clement of Alexandria","sc":22,"sv":10,"ec":22,"ev":10,"p":"Clement of Alexandria/Deuteronomy 22_10.toml"},{"a":"Clement of Alexandria","sc":22,"sv":1,"ec":22,"ev":4,"p":"Clement of Alexandria/Deuteronomy 22_1-4.toml"},{"a":"Ambrose of Milan","sc":22,"sv":5,"ec":22,"ev":5,"p":"Ambrose of Milan/Deuteronomy 22_5.toml"},{"a":"Origen of Alexandria","sc":22,"sv":8,"ec":22,"ev":8,"p":"Origen of Alexandria/Deuteronomy 22_8.toml"}],"11":[{"a":"Paterius","sc":11,"sv":14,"ec":11,"ev":14,"p":"Paterius/Deuteronomy 11_14.toml"},{"a":"Bonaventure","sc":11,"sv":26,"ec":11,"ev":26,"p":"Bonaventure/Deuteronomy 11_26.toml"},{"a":"Bonaventure","sc":11,"sv":10,"ec":11,"ev":10,"p":"Bonaventure/Deuteronomy 11_10.toml"},{"a":"Bonaventure","sc":11,"sv":7,"ec":11,"ev":7,"p":"Bonaventure/Deuteronomy 11_7.toml"},{"a":"Jerome","sc":11,"sv":11,"ec":11,"ev":11,"p":"Jerome/Deuteronomy 11_11.toml"}],"16":[{"a":"Paterius","sc":16,"sv":16,"ec":16,"ev":16,"p":"Paterius/Deuteronomy 16_16.toml"},{"a":"Bonaventure","sc":16,"sv":20,"ec":16,"ev":20,"p":"Bonaventure/Deuteronomy 16_20.toml"},{"a":"Bonaventure","sc":16,"sv":19,"ec":16,"ev":19,"p":"Bonaventure/Deuteronomy 16_19.toml"},{"a":"John Cassian","sc":16,"sv":9,"ec":16,"ev":9,"p":"John Cassian/Deuteronomy 16_9.toml"},{"a":"Caesarius of Arles","sc":16,"sv":19,"ec":16,"ev":19,"p":"Caesarius of Arles/Deuteronomy 16_19.toml"},{"a":"Origen of Alexandria","sc":16,"sv":10,"ec":16,"ev":10,"p":"Origen of Alexandria/Deuteronomy 16_10.toml"},{"a":"Jerome","sc":16,"sv":20,"ec":16,"ev":20,"p":"Jerome/Deuteronomy 16_20.toml"}],"15":[{"a":"Paterius","sc":15,"sv":19,"ec":15,"ev":19,"p":"Paterius/Deuteronomy 15_19.toml"},{"a":"Bonaventure","sc":15,"sv":11,"ec":15,"ev":11,"p":"Bonaventure/Deuteronomy 15_11.toml"},{"a":"Ambrose of Milan","sc":15,"sv":6,"ec":15,"ev":6,"p":"Ambrose of Milan/Deuteronomy 15_6.toml"}],"25":[{"a":"Bonaventure","sc":25,"sv":2,"ec":25,"ev":2,"p":"Bonaventure/Deuteronomy 25_2.toml"},{"a":"Apostolic Constitutions","sc":25,"sv":4,"ec":25,"ev":4,"p":"Apostolic Constitutions/Deuteronomy 25_4.toml"},{"a":"Matthew","sc":25,"sv":5,"ec":25,"ev":5,"p":"Matthew/Deuteronomy 25_5.toml"},{"a":"1 Timothy","sc":25,"sv":4,"ec":25,"ev":4,"p":"1 Timothy/Deuteronomy 25_4.toml"},{"a":"Augustine of Hippo","sc":25,"sv":5,"ec":25,"ev":5,"p":"Augustine of Hippo/Deuteronomy 25_5.toml"},{"a":"Augustine of Hippo","sc":25,"sv":9,"ec":25,"ev":9,"p":"Augustine of Hippo/Deuteronomy 25_9.toml"},{"a":"1 Corinthians","sc":25,"sv":4,"ec":25,"ev":4,"p":"1 Corinthians/Deuteronomy 25_4.toml"}],"21":[{"a":"Bonaventure","sc":21,"sv":18,"ec":21,"ev":18,"p":"Bonaventure/Deuteronomy 21_18.toml"},{"a":"Galatians","sc":21,"sv":23,"ec":21,"ev":23,"p":"Galatians/Deuteronomy 21_23.toml"},{"a":"Clement of Alexandria","sc":21,"sv":13,"ec":21,"ev":13,"p":"Clement of Alexandria/Deuteronomy 21_13.toml"},{"a":"Ambrose of Milan","sc":21,"sv":17,"ec":21,"ev":17,"p":"Ambrose of Milan/Deuteronomy 21_17.toml"},{"a":"Ambrose of Milan","sc":21,"sv":15,"ec":21,"ev":15,"p":"Ambrose of Milan/Deuteronomy 21_15.toml"},{"a":"Origen of Alexandria","sc":21,"sv":10,"ec":21,"ev":11,"p":"Origen of Alexandria/Deuteronomy 21_10-11.toml"},{"a":"Athanasius of Alexandria","sc":21,"sv":23,"ec":21,"ev":23,"p":"Athanasius of Alexandria/Deuteronomy 21_23.toml"}],"17":[{"a":"Bonaventure","sc":17,"sv":12,"ec":17,"ev":12,"p":"Bonaventure/Deuteronomy 17_12.toml"},{"a":"Basil of Caesarea","sc":17,"sv":20,"ec":17,"ev":20,"p":"Basil of Caesarea/Deuteronomy 17_20.toml"},{"a":"Augustine of Hippo","sc":17,"sv":11,"ec":17,"ev":11,"p":"Augustine of Hippo/Deuteronomy 17_11.toml"},{"a":"Tertullian","sc":17,"sv":6,"ec":17,"ev":6,"p":"Tertullian/Deuteronomy 17_6.toml"},{"a":"1 Corinthians","sc":17,"sv":7,"ec":17,"ev":7,"p":"1 Corinthians/Deuteronomy 17_7.toml"}],"23":[{"a":"Bonaventure","sc":23,"sv":23,"ec":23,"ev":23,"p":"Bonaventure/Deuteronomy 23_23.toml"},{"a":"Clement of Alexandria","sc":23,"sv":7,"ec":23,"ev":7,"p":"Clement of Alexandria/Deuteronomy 23_7.toml"},{"a":"Ambrose of Milan","sc":23,"sv":21,"ec":23,"ev":21,"p":"Ambrose of Milan/Deuteronomy 23_21.toml"},{"a":"Ambrose of Milan","sc":23,"sv":19,"ec":23,"ev":19,"p":"Ambrose of Milan/Deuteronomy 23_19.toml"},{"a":"Augustine of Hippo","sc":23,"sv":24,"ec":23,"ev":24,"p":"Augustine of Hippo/Deuteronomy 23_24.toml"}],"27":[{"a":"Galatians","sc":27,"sv":26,"ec":27,"ev":26,"p":"Galatians/Deuteronomy 27_26.toml"},{"a":"Gregory of Nazianzus","sc":27,"sv":5,"ec":27,"ev":5,"p":"Gregory of Nazianzus/Deuteronomy 27_5.toml"},{"a":"Basil of Caesarea","sc":27,"sv":26,"ec":27,"ev":26,"p":"Basil of Caesarea/Deuteronomy 27_26.toml"},{"a":"Irenaeus","sc":27,"sv":18,"ec":27,"ev":18,"p":"Irenaeus/Deuteronomy 27_18.toml"},{"a":"Jerome","sc":27,"sv":15,"ec":27,"ev":15,"p":"Jerome/Deuteronomy 27_15.toml"},{"a":"Jerome","sc":27,"sv":11,"ec":28,"ev":14,"p":"Jerome/Deuteronomy 27_11-28_14.toml"}],"12":[{"a":"Clement of Rome","sc":12,"sv":28,"ec":12,"ev":28,"p":"Clement of Rome/Deuteronomy 12_28.toml"},{"a":"Didache","sc":12,"sv":31,"ec":12,"ev":32,"p":"Didache/Deuteronomy 12_31-32.toml"},{"a":"Augustine of Hippo","sc":12,"sv":3,"ec":12,"ev":3,"p":"Augustine of Hippo/Deuteronomy 12_3.toml"}],"9":[{"a":"Hebrews","sc":9,"sv":19,"ec":9,"ev":19,"p":"Hebrews/Deuteronomy 9_19.toml"},{"a":"Maximus of Turin","sc":9,"sv":9,"ec":9,"ev":9,"p":"Maximus of Turin/Deuteronomy 9_9.toml"},{"a":"John Cassian","sc":9,"sv":4,"ec":9,"ev":4,"p":"John Cassian/Deuteronomy 9_4.toml"},{"a":"Cyril of Jerusalem","sc":9,"sv":10,"ec":9,"ev":10,"p":"Cyril of Jerusalem/Deuteronomy 9_10.toml"},{"a":"Cyril of Jerusalem","sc":9,"sv":20,"ec":9,"ev":20,"p":"Cyril of Jerusalem/Deuteronomy 9_20.toml"},{"a":"Origen of Alexandria","sc":9,"sv":9,"ec":9,"ev":9,"p":"Origen of Alexandria/Deuteronomy 9_9.toml"},{"a":"Augustine of Hippo","sc":9,"sv":9,"ec":9,"ev":9,"p":"Augustine of Hippo/Deuteronomy 9_9.toml"}],"34":[{"a":"Paulus Orosius","sc":34,"sv":4,"ec":34,"ev":4,"p":"Paulus Orosius/Deuteronomy 34_4.toml"},{"a":"Gregory of Nyssa","sc":34,"sv":5,"ec":34,"ev":5,"p":"Gregory of Nyssa/Deuteronomy 34_5.toml"},{"a":"Cyril of Jerusalem","sc":34,"sv":9,"ec":34,"ev":9,"p":"Cyril of Jerusalem/Deuteronomy 34_9.toml"},{"a":"Ambrose of Milan","sc":34,"sv":5,"ec":34,"ev":5,"p":"Ambrose of Milan/Deuteronomy 34_5.toml"},{"a":"Aphrahat the Persian Sage","sc":34,"sv":6,"ec":34,"ev":6,"p":"Aphrahat the Persian Sage/Deuteronomy 34_6.toml"},{"a":"Paulinus of Nola","sc":34,"sv":6,"ec":34,"ev":6,"p":"Paulinus of Nola/Deuteronomy 34_6.toml"}],"29":[{"a":"Romans","sc":29,"sv":3,"ec":29,"ev":4,"p":"Romans/Deuteronomy 29_3-4.toml"},{"a":"Origen of Alexandria","sc":29,"sv":23,"ec":29,"ev":23,"p":"Origen of Alexandria/Deuteronomy 29_23.toml"}],"19":[{"a":"Gregory the Dialogist","sc":19,"sv":5,"ec":19,"ev":5,"p":"Gregory the Dialogist/Deuteronomy 19_5.toml"},{"a":"Maximus of Turin","sc":19,"sv":15,"ec":19,"ev":15,"p":"Maximus of Turin/Deuteronomy 19_15.toml"},{"a":"2 Corinthians","sc":19,"sv":15,"ec":19,"ev":15,"p":"2 Corinthians/Deuteronomy 19_15.toml"},{"a":"Matthew","sc":19,"sv":15,"ec":19,"ev":15,"p":"Matthew/Deuteronomy 19_15.toml"},{"a":"Cyril of Jerusalem","sc":19,"sv":15,"ec":19,"ev":15,"p":"Cyril of Jerusalem/Deuteronomy 19_15.toml"},{"a":"Ambrose of Milan","sc":19,"sv":14,"ec":19,"ev":14,"p":"Ambrose of Milan/Deuteronomy 19_14.toml"},{"a":"Augustine of Hippo","sc":19,"sv":15,"ec":19,"ev":15,"p":"Augustine of Hippo/Deuteronomy 19_15.toml"},{"a":"Jerome","sc":19,"sv":5,"ec":19,"ev":5,"p":"Jerome/Deuteronomy 19_5.toml"}],"18":[{"a":"Acts","sc":18,"sv":15,"ec":18,"ev":15,"p":"Acts/Deuteronomy 18_15.toml"},{"a":"Acts","sc":18,"sv":18,"ec":18,"ev":19,"p":"Acts/Deuteronomy 18_18-19.toml"},{"a":"Origen of Alexandria","sc":18,"sv":15,"ec":18,"ev":15,"p":"Origen of Alexandria/Deuteronomy 18_15.toml"},{"a":"Origen of Alexandria","sc":18,"sv":20,"ec":18,"ev":20,"p":"Origen of Alexandria/Deuteronomy 18_20.toml"},{"a":"Cosmas Indicopleustes","sc":18,"sv":15,"ec":18,"ev":15,"p":"Cosmas Indicopleustes/Deuteronomy 18_15.toml"},{"a":"CS Lewis","sc":18,"sv":20,"ec":18,"ev":20,"p":"CS Lewis/Deuteronomy 18_20.toml"},{"a":"Augustine of Hippo","sc":18,"sv":15,"ec":18,"ev":15,"p":"Augustine of Hippo/Deuteronomy 18_15.toml"}],"28":[{"a":"Ephrem the Syrian","sc":28,"sv":29,"ec":28,"ev":29,"p":"Ephrem the Syrian/Deuteronomy 28_29.toml"},{"a":"Ambrose of Milan","sc":28,"sv":23,"ec":28,"ev":23,"p":"Ambrose of Milan/Deuteronomy 28_23.toml"},{"a":"Ambrose of Milan","sc":28,"sv":12,"ec":28,"ev":12,"p":"Ambrose of Milan/Deuteronomy 28_12.toml"},{"a":"Basil of Caesarea","sc":28,"sv":23,"ec":28,"ev":23,"p":"Basil of Caesarea/Deuteronomy 28_23.toml"},{"a":"Basil of Caesarea","sc":28,"sv":5,"ec":28,"ev":5,"p":"Basil of Caesarea/Deuteronomy 28_5.toml"},{"a":"Athanasius of Alexandria","sc":28,"sv":66,"ec":28,"ev":66,"p":"Athanasius of Alexandria/Deuteronomy 28_66.toml"},{"a":"Tertullian","sc":28,"sv":66,"ec":28,"ev":66,"p":"Tertullian/Deuteronomy 28_66.toml"},{"a":"Jerome","sc":27,"sv":11,"ec":28,"ev":14,"p":"Jerome/Deuteronomy 27_11-28_14.toml"}],"7":[{"a":"John Cassian","sc":7,"sv":1,"ec":7,"ev":1,"p":"John Cassian/Deuteronomy 7_1.toml"},{"a":"Augustine of Hippo","sc":7,"sv":5,"ec":7,"ev":5,"p":"Augustine of Hippo/Deuteronomy 7_5.toml"}],"26":[{"a":"Clement of Alexandria","sc":26,"sv":18,"ec":26,"ev":18,"p":"Clement of Alexandria/Deuteronomy 26_18.toml"}],"20":[{"a":"Clement of Alexandria","sc":20,"sv":19,"ec":20,"ev":19,"p":"Clement of Alexandria/Deuteronomy 20_19.toml"},{"a":"Clement of Alexandria","sc":20,"sv":5,"ec":20,"ev":5,"p":"Clement of Alexandria/Deuteronomy 20_5.toml"}],"14":[{"a":"Clement of Alexandria","sc":14,"sv":3,"ec":14,"ev":3,"p":"Clement of Alexandria/Deuteronomy 14_3.toml"},{"a":"Ambrose of Milan","sc":14,"sv":4,"ec":14,"ev":4,"p":"Ambrose of Milan/Deuteronomy 14_4.toml"}],"1":[{"a":"Didache","sc":1,"sv":16,"ec":1,"ev":17,"p":"Didache/Deuteronomy 1_16-17.toml"},{"a":"Origen of Alexandria","sc":1,"sv":31,"ec":1,"ev":31,"p":"Origen of Alexandria/Deuteronomy 1_31.toml"},{"a":"Origen of Alexandria","sc":1,"sv":1,"ec":1,"ev":1,"p":"Origen of Alexandria/Deuteronomy 1_1.toml"}],"13":[{"a":"Pacian of Barcelona","sc":13,"sv":9,"ec":13,"ev":9,"p":"Pacian of Barcelona/Deuteronomy 13_9.toml"},{"a":"Vincent of Lérins","sc":13,"sv":3,"ec":13,"ev":3,"p":"Vincent of Lérins/Deuteronomy 13_3.toml"},{"a":"Augustine of Hippo","sc":13,"sv":3,"ec":13,"ev":3,"p":"Augustine of Hippo/Deuteronomy 13_3.toml"}]}